[
	{
		"iconName": "square-minus",
		"title": "Square Minus",
		"library": "faregular",
		"prefix": "far",
		"tags": ["remove", "subtract", "less"]
	},
	{
		"iconName": "minus-square",
		"title": "Minus Square",
		"library": "faregular",
		"prefix": "far",
		"tags": ["remove", "subtract", "less"]
	},
	{
		"iconName": "calendar-check",
		"title": "Calendar Check",
		"library": "faregular",
		"prefix": "far",
		"tags": ["date", "schedule", "planner"]
	},
	{
		"iconName": "face-kiss",
		"title": "Face Kiss",
		"library": "faregular",
		"prefix": "far",
		"tags": ["love", "kiss", "heart"]
	},
	{
		"iconName": "kiss",
		"title": "Kiss",
		"library": "faregular",
		"prefix": "far",
		"tags": ["love", "kiss", "heart"]
	},
	{
		"iconName": "paste",
		"title": "Paste",
		"library": "faregular",
		"prefix": "far",
		"tags": ["copy", "paste", "clipboard"]
	},
	{
		"iconName": "file-clipboard",
		"title": "File Clipboard",
		"library": "faregular",
		"prefix": "far",
		"tags": ["document", "doc", "paper"]
	},
	{
		"iconName": "hand-point-left",
		"title": "Hand Point Left",
		"library": "faregular",
		"prefix": "far",
		"tags": ["back", "previous", "west"]
	},
	{
		"iconName": "file-excel",
		"title": "File Excel",
		"library": "faregular",
		"prefix": "far",
		"tags": ["document", "doc", "paper"]
	},
	{
		"iconName": "envelope",
		"title": "Envelope",
		"library": "faregular",
		"prefix": "far",
		"tags": ["email", "mail", "message"]
	},
	{
		"iconName": "square-caret-down",
		"title": "Square Caret Down",
		"library": "faregular",
		"prefix": "far",
		"tags": ["bottom", "descend", "south"]
	},
	{
		"iconName": "caret-square-down",
		"title": "Caret Square Down",
		"library": "faregular",
		"prefix": "far",
		"tags": ["bottom", "descend", "south"]
	},
	{
		"iconName": "truck",
		"title": "Truck",
		"library": "faregular",
		"prefix": "far",
		"tags": ["delivery", "shipping", "logistics"]
	},
	{
		"iconName": "bell",
		"title": "Bell",
		"library": "faregular",
		"prefix": "far",
		"tags": ["notification", "alert", "reminder"]
	},
	{
		"iconName": "message",
		"title": "Message",
		"library": "faregular",
		"prefix": "far",
		"tags": ["email", "mail", "message"]
	},
	{
		"iconName": "comment-alt",
		"title": "Comment Alt",
		"library": "faregular",
		"prefix": "far",
		"tags": ["reply", "message", "feedback"]
	},
	{
		"iconName": "face-dizzy",
		"title": "Face Dizzy",
		"library": "faregular",
		"prefix": "far",
		"tags": ["dizzy", "headache", "unwell"]
	},
	{
		"iconName": "dizzy",
		"title": "Dizzy",
		"library": "faregular",
		"prefix": "far",
		"tags": ["dizzy", "headache", "unwell"]
	},
	{
		"iconName": "calendar-days",
		"title": "Calendar Days",
		"library": "faregular",
		"prefix": "far",
		"tags": ["date", "schedule", "planner"]
	},
	{
		"iconName": "calendar-alt",
		"title": "Calendar Alt",
		"library": "faregular",
		"prefix": "far",
		"tags": ["date", "schedule", "planner"]
	},
	{
		"iconName": "hand-point-up",
		"title": "Hand Point Up",
		"library": "faregular",
		"prefix": "far",
		"tags": ["top", "ascend", "north"]
	},
	{
		"iconName": "hand-lizard",
		"title": "Hand Lizard",
		"library": "faregular",
		"prefix": "far",
		"tags": ["lizard", "hand", "rock"]
	},
	{
		"iconName": "square-full",
		"title": "Square Full",
		"library": "faregular",
		"prefix": "far",
		"tags": ["square", "full", "fill"]
	},
	{
		"iconName": "circle-pause",
		"title": "Circle Pause",
		"library": "faregular",
		"prefix": "far",
		"tags": ["hold", "wait", "stop"]
	},
	{
		"iconName": "pause-circle",
		"title": "Pause Circle",
		"library": "faregular",
		"prefix": "far",
		"tags": ["hold", "wait", "stop"]
	},
	{
		"iconName": "hard-drive",
		"title": "Hard Drive",
		"library": "faregular",
		"prefix": "far",
		"tags": ["disk", "hdd", "flash disk"]
	},
	{
		"iconName": "hdd",
		"title": "Hdd",
		"library": "faregular",
		"prefix": "far",
		"tags": ["floppy", "disk", "save"]
	},
	{
		"iconName": "file-zipper",
		"title": "File Zipper",
		"library": "faregular",
		"prefix": "far",
		"tags": ["document", "doc", "paper"]
	},
	{
		"iconName": "file-archive",
		"title": "File Archive",
		"library": "faregular",
		"prefix": "far",
		"tags": ["document", "doc", "paper"]
	},
	{
		"iconName": "floppy-disk",
		"title": "Floppy Disk",
		"library": "faregular",
		"prefix": "far",
		"tags": ["save", "floppy", "disk"]
	},
	{
		"iconName": "save",
		"title": "Save",
		"library": "faregular",
		"prefix": "far",
		"tags": ["download", "store", "bookmark"]
	},
	{
		"iconName": "face-grin-tongue-squint",
		"title": "Face Grin Tongue Squint",
		"library": "faregular",
		"prefix": "far",
		"tags": ["tongue", "squint", "smile"]
	},
	{
		"iconName": "grin-tongue-squint",
		"title": "Grin Tongue Squint",
		"library": "faregular",
		"prefix": "far",
		"tags": ["tongue", "squint", "smile"]
	},
	{
		"iconName": "camera",
		"title": "Camera",
		"library": "faregular",
		"prefix": "far",
		"tags": ["photo", "picture", "shoot"]
	},
	{
		"iconName": "camera-alt",
		"title": "Camera Alt",
		"library": "faregular",
		"prefix": "far",
		"tags": ["photo", "picture", "shoot"]
	},
	{
		"iconName": "face-grin-stars",
		"title": "Face Grin Stars",
		"library": "faregular",
		"prefix": "far",
		"tags": ["favorite", "rating", "bookmark"]
	},
	{
		"iconName": "grin-stars",
		"title": "Grin Stars",
		"library": "faregular",
		"prefix": "far",
		"tags": ["favorite", "rating", "bookmark"]
	},
	{
		"iconName": "eye",
		"title": "Eye",
		"library": "faregular",
		"prefix": "far",
		"tags": ["view", "see", "preview"]
	},
	{
		"iconName": "face-sad-tear",
		"title": "Face Sad Tear",
		"library": "faregular",
		"prefix": "far",
		"tags": ["sad", "tear", "cry"]
	},
	{
		"iconName": "sad-tear",
		"title": "Sad Tear",
		"library": "faregular",
		"prefix": "far",
		"tags": ["sad", "tear", "cry"]
	},
	{
		"iconName": "share-from-square",
		"title": "Share From Square",
		"library": "faregular",
		"prefix": "far",
		"tags": ["export", "forward", "send"]
	},
	{
		"iconName": "share-square",
		"title": "Share Square",
		"library": "faregular",
		"prefix": "far",
		"tags": ["export", "forward", "send"]
	},
	{
		"iconName": "note-sticky",
		"title": "Note Sticky",
		"library": "faregular",
		"prefix": "far",
		"tags": ["sticky", "note", "memo"]
	},
	{
		"iconName": "sticky-note",
		"title": "Sticky Note",
		"library": "faregular",
		"prefix": "far",
		"tags": ["sticky", "note", "memo"]
	},
	{
		"iconName": "hand-back-fist",
		"title": "Hand Back Fist",
		"library": "faregular",
		"prefix": "far",
		"tags": ["fist", "hand", "back"]
	},
	{
		"iconName": "hand-rock",
		"title": "Hand Rock",
		"library": "faregular",
		"prefix": "far",
		"tags": ["rock", "hand", "fist"]
	},
	{
		"iconName": "chess-queen",
		"title": "Chess Queen",
		"library": "faregular",
		"prefix": "far",
		"tags": ["queen", "chess", "game"]
	},
	{
		"iconName": "face-grin-tears",
		"title": "Face Grin Tears",
		"library": "faregular",
		"prefix": "far",
		"tags": ["sad", "tear", "cry"]
	},
	{
		"iconName": "grin-tears",
		"title": "Grin Tears",
		"library": "faregular",
		"prefix": "far",
		"tags": ["sad", "tear", "cry"]
	},
	{
		"iconName": "pen-to-square",
		"title": "Pen To Square",
		"library": "faregular",
		"prefix": "far",
		"tags": ["edit", "write", "draw"]
	},
	{
		"iconName": "edit",
		"title": "Edit",
		"library": "faregular",
		"prefix": "far",
		"tags": ["pencil", "modify", "write"]
	},
	{
		"iconName": "face-grin-beam-sweat",
		"title": "Face Grin Beam Sweat",
		"library": "faregular",
		"prefix": "far",
		"tags": ["happy", "emoji", "grin"]
	},
	{
		"iconName": "grin-beam-sweat",
		"title": "Grin Beam Sweat",
		"library": "faregular",
		"prefix": "far",
		"tags": ["happy", "emoji", "grin"]
	},
	{
		"iconName": "clock",
		"title": "Clock",
		"library": "faregular",
		"prefix": "far",
		"tags": ["time", "watch", "schedule"]
	},
	{
		"iconName": "clock-four",
		"title": "Clock Four",
		"library": "faregular",
		"prefix": "far",
		"tags": ["time", "watch", "schedule"]
	},
	{
		"iconName": "face-laugh-wink",
		"title": "Face Laugh Wink",
		"library": "faregular",
		"prefix": "far",
		"tags": ["happy", "emoji", "grin"]
	},
	{
		"iconName": "laugh-wink",
		"title": "Laugh Wink",
		"library": "faregular",
		"prefix": "far",
		"tags": ["happy", "emoji", "grin"]
	},
	{
		"iconName": "paper-plane",
		"title": "Paper Plane",
		"library": "faregular",
		"prefix": "far",
		"tags": ["like", "love", "favorite"]
	},
	{
		"iconName": "heart",
		"title": "Heart",
		"library": "faregular",
		"prefix": "far",
		"tags": ["like", "love", "favorite"]
	},
	{
		"iconName": "font-awesome",
		"title": "Font Awesome",
		"library": "faregular",
		"prefix": "far",
		"tags": []
	},
	{
		"iconName": "font-awesome-flag",
		"title": "Font Awesome Flag",
		"library": "faregular",
		"prefix": "far",
		"tags": ["report", "marker", "pin"]
	},
	{
		"iconName": "font-awesome-logo-full",
		"title": "Font Awesome Logo Full",
		"library": "faregular",
		"prefix": "far",
		"tags": []
	},
	{
		"iconName": "clone",
		"title": "Clone",
		"library": "faregular",
		"prefix": "far",
		"tags": ["copy", "duplicate", "clone"]
	},
	{
		"iconName": "folder-open",
		"title": "Folder Open",
		"library": "faregular",
		"prefix": "far",
		"tags": ["directory", "catalog", "container"]
	},
	{
		"iconName": "window-minimize",
		"title": "Window Minimize",
		"library": "faregular",
		"prefix": "far",
		"tags": ["minimize", "shrink", "window"]
	},
	{
		"iconName": "star-half",
		"title": "Star Half",
		"library": "faregular",
		"prefix": "far",
		"tags": ["favorite", "rating", "bookmark"]
	},
	{
		"iconName": "alarm-clock",
		"title": "Alarm Clock",
		"library": "faregular",
		"prefix": "far",
		"tags": ["alert", "timer", "time"]
	},
	{
		"iconName": "newspaper",
		"title": "Newspaper",
		"library": "faregular",
		"prefix": "far",
		"tags": ["magazine", "news", "paper"]
	},
	{
		"iconName": "hospital",
		"title": "Hospital",
		"library": "faregular",
		"prefix": "far",
		"tags": ["hospital", "medical", "health"]
	},
	{
		"iconName": "hospital-alt",
		"title": "Hospital Alt",
		"library": "faregular",
		"prefix": "far",
		"tags": ["hospital", "medical", "health"]
	},
	{
		"iconName": "hospital-wide",
		"title": "Hospital Wide",
		"library": "faregular",
		"prefix": "far",
		"tags": ["hospital", "medical", "health"]
	},
	{
		"iconName": "circle-stop",
		"title": "Circle Stop",
		"library": "faregular",
		"prefix": "far",
		"tags": ["end", "halt", "square"]
	},
	{
		"iconName": "stop-circle",
		"title": "Stop Circle",
		"library": "faregular",
		"prefix": "far",
		"tags": ["end", "halt", "square"]
	},
	{
		"iconName": "object-ungroup",
		"title": "Object Ungroup",
		"library": "faregular",
		"prefix": "far",
		"tags": ["group", "ungroup", "split"]
	},
	{
		"iconName": "comment",
		"title": "Comment",
		"library": "faregular",
		"prefix": "far",
		"tags": ["reply", "message", "feedback"]
	},
	{
		"iconName": "chess-pawn",
		"title": "Chess Pawn",
		"library": "faregular",
		"prefix": "far",
		"tags": ["pawn", "chess", "game"]
	},
	{
		"iconName": "calendar-plus",
		"title": "Calendar Plus",
		"library": "faregular",
		"prefix": "far",
		"tags": ["date", "schedule", "planner"]
	},
	{
		"iconName": "clipboard",
		"title": "Clipboard",
		"library": "faregular",
		"prefix": "far",
		"tags": ["copy", "paste", "clipboard"]
	},
	{
		"iconName": "thumbs-down",
		"title": "Thumbs Down",
		"library": "faregular",
		"prefix": "far",
		"tags": ["bottom", "descend", "south"]
	},
	{
		"iconName": "id-badge",
		"title": "Id Badge",
		"library": "faregular",
		"prefix": "far",
		"tags": ["id", "card", "badge"]
	},
	{
		"iconName": "square-check",
		"title": "Square Check",
		"library": "faregular",
		"prefix": "far",
		"tags": ["tick", "confirm", "done"]
	},
	{
		"iconName": "check-square",
		"title": "Check Square",
		"library": "faregular",
		"prefix": "far",
		"tags": ["tick", "confirm", "done"]
	},
	{
		"iconName": "chess-bishop",
		"title": "Chess Bishop",
		"library": "faregular",
		"prefix": "far",
		"tags": ["bishop", "chess", "game"]
	},
	{
		"iconName": "envelope-open",
		"title": "Envelope Open",
		"library": "faregular",
		"prefix": "far",
		"tags": ["unlock", "start", "enter"]
	},
	{
		"iconName": "circle-xmark",
		"title": "Circle Xmark",
		"library": "faregular",
		"prefix": "far",
		"tags": ["delete", "cancel", "close"]
	},
	{
		"iconName": "times-circle",
		"title": "Times Circle",
		"library": "faregular",
		"prefix": "far",
		"tags": ["delete", "cancel", "close", "circle"]
	},
	{
		"iconName": "xmark-circle",
		"title": "Xmark Circle",
		"library": "faregular",
		"prefix": "far",
		"tags": ["delete", "cancel", "close", "circle"]
	},
	{
		"iconName": "square-caret-up",
		"title": "Square Caret Up",
		"library": "faregular",
		"prefix": "far",
		"tags": ["top", "ascend", "north"]
	},
	{
		"iconName": "caret-square-up",
		"title": "Caret Square Up",
		"library": "faregular",
		"prefix": "far",
		"tags": ["top", "ascend", "north"]
	},
	{
		"iconName": "file-image",
		"title": "File Image",
		"library": "faregular",
		"prefix": "far",
		"tags": ["document", "doc", "paper"]
	},
	{
		"iconName": "square-caret-right",
		"title": "Square Caret Right",
		"library": "faregular",
		"prefix": "far",
		"tags": ["next", "forward", "east"]
	},
	{
		"iconName": "caret-square-right",
		"title": "Caret Square Right",
		"library": "faregular",
		"prefix": "far",
		"tags": ["next", "forward", "east"]
	},
	{
		"iconName": "sun",
		"title": "Sun",
		"library": "faregular",
		"prefix": "far",
		"tags": ["brightness", "day", "light"]
	},
	{
		"iconName": "image",
		"title": "Image",
		"library": "faregular",
		"prefix": "far",
		"tags": ["photo", "picture", "media"]
	},
	{
		"iconName": "lightbulb",
		"title": "Lightbulb",
		"library": "faregular",
		"prefix": "far",
		"tags": ["idea", "light", "bulb"]
	},
	{
		"iconName": "address-card",
		"title": "Address Card",
		"library": "faregular",
		"prefix": "far",
		"tags": ["location", "place", "contact"]
	},
	{
		"iconName": "contact-card",
		"title": "Contact Card",
		"library": "faregular",
		"prefix": "far",
		"tags": ["location", "place", "contact"]
	},
	{
		"iconName": "vcard",
		"title": "Vcard",
		"library": "faregular",
		"prefix": "far",
		"tags": ["location", "place", "contact"]
	},
	{
		"iconName": "face-meh",
		"title": "Face Meh",
		"library": "faregular",
		"prefix": "far",
		"tags": ["neutral", "meh", "indifference"]
	},
	{
		"iconName": "meh",
		"title": "Meh",
		"library": "faregular",
		"prefix": "far",
		"tags": ["neutral", "meh", "indifference"]
	},
	{
		"iconName": "map",
		"title": "Map",
		"library": "faregular",
		"prefix": "far",
		"tags": ["location", "route", "navigation"]
	},
	{
		"iconName": "hand-point-down",
		"title": "Hand Point Down",
		"library": "faregular",
		"prefix": "far",
		"tags": ["bottom", "descend", "south"]
	},
	{
		"iconName": "face-meh-blank",
		"title": "Face Meh Blank",
		"library": "faregular",
		"prefix": "far",
		"tags": ["neutral", "meh", "indifference"]
	},
	{
		"iconName": "meh-blank",
		"title": "Meh Blank",
		"library": "faregular",
		"prefix": "far",
		"tags": ["neutral", "meh", "indifference"]
	},
	{
		"iconName": "face-grin-tongue",
		"title": "Face Grin Tongue",
		"library": "faregular",
		"prefix": "far",
		"tags": ["tongue", "smile", "grin"]
	},
	{
		"iconName": "grin-tongue",
		"title": "Grin Tongue",
		"library": "faregular",
		"prefix": "far",
		"tags": ["tongue", "smile", "grin"]
	},
	{
		"iconName": "futbol",
		"title": "Futbol",
		"library": "faregular",
		"prefix": "far",
		"tags": ["soccer", "football", "ball"]
	},
	{
		"iconName": "futbol-ball",
		"title": "Futbol Ball",
		"library": "faregular",
		"prefix": "far",
		"tags": ["soccer", "football", "ball"]
	},
	{
		"iconName": "soccer-ball",
		"title": "Soccer Ball",
		"library": "faregular",
		"prefix": "far",
		"tags": ["soccer", "football", "ball"]
	},
	{
		"iconName": "face-surprise",
		"title": "Face Surprise",
		"library": "faregular",
		"prefix": "far",
		"tags": ["surprise", "shock", "surprise"]
	},
	{
		"iconName": "surprise",
		"title": "Surprise",
		"library": "faregular",
		"prefix": "far",
		"tags": ["surprise", "shock", "surprise"]
	},
	{
		"iconName": "folder",
		"title": "Folder",
		"library": "faregular",
		"prefix": "far",
		"tags": ["directory", "catalog", "container"]
	},
	{
		"iconName": "folder-blank",
		"title": "Folder Blank",
		"library": "faregular",
		"prefix": "far",
		"tags": ["directory", "catalog", "container"]
	},
	{
		"iconName": "cloud",
		"title": "Cloud",
		"library": "faregular",
		"prefix": "far",
		"tags": ["storage", "server", "sync"]
	},
	{
		"iconName": "circle",
		"title": "Circle",
		"library": "faregular",
		"prefix": "far",
		"tags": ["circle", "round", "shape"]
	},
	{
		"iconName": "face-grin-squint",
		"title": "Face Grin Squint",
		"library": "faregular",
		"prefix": "far",
		"tags": ["happy", "emoji", "grin"]
	},
	{
		"iconName": "grin-squint",
		"title": "Grin Squint",
		"library": "faregular",
		"prefix": "far",
		"tags": ["happy", "emoji", "grin"]
	},
	{
		"iconName": "circle-user",
		"title": "Circle User",
		"library": "faregular",
		"prefix": "far",
		"tags": ["person", "profile", "customer"]
	},
	{
		"iconName": "user-circle",
		"title": "User Circle",
		"library": "faregular",
		"prefix": "far",
		"tags": ["person", "profile", "customer"]
	},
	{
		"iconName": "rectangle-list",
		"title": "Rectangle List",
		"library": "faregular",
		"prefix": "far",
		"tags": ["items", "bullets", "menu"]
	},
	{
		"iconName": "list-alt",
		"title": "List Alt",
		"library": "faregular",
		"prefix": "far",
		"tags": ["items", "bullets", "menu"]
	},
	{
		"iconName": "hand",
		"title": "Hand",
		"library": "faregular",
		"prefix": "far",
		"tags": ["hand", "finger", "gesture"]
	},
	{
		"iconName": "hand-paper",
		"title": "Hand Paper",
		"library": "faregular",
		"prefix": "far",
		"tags": ["hand", "finger", "gesture"]
	},
	{
		"iconName": "thumbs-up",
		"title": "Thumbs Up",
		"library": "faregular",
		"prefix": "far",
		"tags": ["top", "ascend", "north"]
	},
	{
		"iconName": "building",
		"title": "Building",
		"library": "faregular",
		"prefix": "far",
		"tags": ["building", "house", "home"]
	},
	{
		"iconName": "chess-rook",
		"title": "Chess Rook",
		"library": "faregular",
		"prefix": "far",
		"tags": ["rook", "chess", "game"]
	},
	{
		"iconName": "circle-question",
		"title": "Circle Question",
		"library": "faregular",
		"prefix": "far",
		"tags": ["question", "help", "support"]
	},
	{
		"iconName": "question-circle",
		"title": "Question Circle",
		"library": "faregular",
		"prefix": "far",
		"tags": ["question", "help", "support"]
	},
	{
		"iconName": "file",
		"title": "File",
		"library": "faregular",
		"prefix": "far",
		"tags": ["document", "doc", "paper"]
	},
	{
		"iconName": "face-sad-cry",
		"title": "Face Sad Cry",
		"library": "faregular",
		"prefix": "far",
		"tags": ["sad", "tear", "cry"]
	},
	{
		"iconName": "sad-cry",
		"title": "Sad Cry",
		"library": "faregular",
		"prefix": "far",
		"tags": ["sad", "tear", "cry"]
	},
	{
		"iconName": "calendar-minus",
		"title": "Calendar Minus",
		"library": "faregular",
		"prefix": "far",
		"tags": ["date", "schedule", "planner"]
	},
	{
		"iconName": "face-tired",
		"title": "Face Tired",
		"library": "faregular",
		"prefix": "far",
		"tags": ["tired", "sleepy", "sleep"]
	},
	{
		"iconName": "tired",
		"title": "Tired",
		"library": "faregular",
		"prefix": "far",
		"tags": ["tired", "sleepy", "sleep"]
	},
	{
		"iconName": "hand-point-right",
		"title": "Hand Point Right",
		"library": "faregular",
		"prefix": "far",
		"tags": ["next", "forward", "east"]
	},
	{
		"iconName": "circle-up",
		"title": "Circle Up",
		"library": "faregular",
		"prefix": "far",
		"tags": ["top", "ascend", "north"]
	},
	{
		"iconName": "arrow-alt-circle-up",
		"title": "Arrow Alt Circle Up",
		"library": "faregular",
		"prefix": "far",
		"tags": ["top", "ascend", "north"]
	},
	{
		"iconName": "hand-scissors",
		"title": "Hand Scissors",
		"library": "faregular",
		"prefix": "far",
		"tags": ["scissors", "cut", "slice"]
	},
	{
		"iconName": "gem",
		"title": "Gem",
		"library": "faregular",
		"prefix": "far",
		"tags": ["diamond", "jewel", "precious"]
	},
	{
		"iconName": "rectangle-xmark",
		"title": "Rectangle Xmark",
		"library": "faregular",
		"prefix": "far",
		"tags": ["delete", "cancel", "close"]
	},
	{
		"iconName": "rectangle-times",
		"title": "Rectangle Times",
		"library": "faregular",
		"prefix": "far",
		"tags": ["delete", "cancel", "close"]
	},
	{
		"iconName": "times-rectangle",
		"title": "Times Rectangle",
		"library": "faregular",
		"prefix": "far",
		"tags": ["delete", "cancel", "close"]
	},
	{
		"iconName": "window-close",
		"title": "Window Close",
		"library": "faregular",
		"prefix": "far",
		"tags": ["delete", "cancel", "close"]
	},
	{
		"iconName": "trash-can",
		"title": "Trash Can",
		"library": "faregular",
		"prefix": "far",
		"tags": ["bin", "delete", "remove"]
	},
	{
		"iconName": "trash-alt",
		"title": "Trash Alt",
		"library": "faregular",
		"prefix": "far",
		"tags": ["bin", "delete", "remove"]
	},
	{
		"iconName": "life-ring",
		"title": "Life Ring",
		"library": "faregular",
		"prefix": "far",
		"tags": ["copyright", "legal", "license"]
	},
	{
		"iconName": "copyright",
		"title": "Copyright",
		"library": "faregular",
		"prefix": "far",
		"tags": ["copyright", "legal", "license"]
	},
	{
		"iconName": "circle-left",
		"title": "Circle Left",
		"library": "faregular",
		"prefix": "far",
		"tags": ["back", "previous", "west"]
	},
	{
		"iconName": "arrow-alt-circle-left",
		"title": "Arrow Alt Circle Left",
		"library": "faregular",
		"prefix": "far",
		"tags": ["back", "previous", "west"]
	},
	{
		"iconName": "calendar",
		"title": "Calendar",
		"library": "faregular",
		"prefix": "far",
		"tags": ["date", "schedule", "planner"]
	},
	{
		"iconName": "face-frown-open",
		"title": "Face Frown Open",
		"library": "faregular",
		"prefix": "far",
		"tags": ["unlock", "start", "enter"]
	},
	{
		"iconName": "frown-open",
		"title": "Frown Open",
		"library": "faregular",
		"prefix": "far",
		"tags": ["unlock", "start", "enter"]
	},
	{
		"iconName": "chart-bar",
		"title": "Chart Bar",
		"library": "faregular",
		"prefix": "far",
		"tags": ["chart", "graph", "data"]
	},
	{
		"iconName": "bar-chart",
		"title": "Bar Chart",
		"library": "faregular",
		"prefix": "far",
		"tags": ["chart", "graph", "data"]
	},
	{
		"iconName": "house",
		"title": "House",
		"library": "faregular",
		"prefix": "far",
		"tags": ["house", "apartment", "property"]
	},
	{
		"iconName": "home",
		"title": "Home",
		"library": "faregular",
		"prefix": "far",
		"tags": ["house", "apartment", "property"]
	},
	{
		"iconName": "home-alt",
		"title": "Home Alt",
		"library": "faregular",
		"prefix": "far",
		"tags": ["house", "apartment", "property"]
	},
	{
		"iconName": "home-lg-alt",
		"title": "Home Lg Alt",
		"library": "faregular",
		"prefix": "far",
		"tags": ["house", "apartment", "property"]
	},
	{
		"iconName": "face-frown",
		"title": "Face Frown",
		"library": "faregular",
		"prefix": "far",
		"tags": ["sad", "tear", "cry"]
	},
	{
		"iconName": "frown",
		"title": "Frown",
		"library": "faregular",
		"prefix": "far",
		"tags": ["sad", "tear", "cry"]
	},
	{
		"iconName": "user",
		"title": "User",
		"library": "faregular",
		"prefix": "far",
		"tags": ["person", "profile", "customer"]
	},
	{
		"iconName": "user-alt",
		"title": "User Alt",
		"library": "faregular",
		"prefix": "far",
		"tags": ["person", "profile", "customer"]
	},
	{
		"iconName": "user-large",
		"title": "User Large",
		"library": "faregular",
		"prefix": "far",
		"tags": ["person", "profile", "customer"]
	},
	{
		"iconName": "snowflake",
		"title": "Snowflake",
		"library": "faregular",
		"prefix": "far",
		"tags": ["snow", "flake", "winter"]
	},
	{
		"iconName": "bookmark",
		"title": "Bookmark",
		"library": "faregular",
		"prefix": "far",
		"tags": ["favorite", "save", "mark"]
	},
	{
		"iconName": "square-caret-left",
		"title": "Square Caret Left",
		"library": "faregular",
		"prefix": "far",
		"tags": ["back", "previous", "west"]
	},
	{
		"iconName": "caret-square-left",
		"title": "Caret Square Left",
		"library": "faregular",
		"prefix": "far",
		"tags": ["back", "previous", "west"]
	},
	{
		"iconName": "handshake",
		"title": "Handshake",
		"library": "faregular",
		"prefix": "far",
		"tags": ["business", "meeting", "agreement", "negotiation"]
	},
	{
		"iconName": "handshake-alt",
		"title": "Handshake Alt",
		"library": "faregular",
		"prefix": "far",
		"tags": ["business", "meeting", "agreement", "negotiation"]
	},
	{
		"iconName": "handshake-simple",
		"title": "Handshake Simple",
		"library": "faregular",
		"prefix": "far",
		"tags": ["business", "deal", "negotiation"]
	},
	{
		"iconName": "face-smile-wink",
		"title": "Face Smile Wink",
		"library": "faregular",
		"prefix": "far",
		"tags": ["happy", "emoji", "grin"]
	},
	{
		"iconName": "smile-wink",
		"title": "Smile Wink",
		"library": "faregular",
		"prefix": "far",
		"tags": ["happy", "emoji", "grin"]
	},
	{
		"iconName": "face-grin-squint-tears",
		"title": "Face Grin Squint Tears",
		"library": "faregular",
		"prefix": "far",
		"tags": ["happy", "emoji", "grin"]
	},
	{
		"iconName": "grin-squint-tears",
		"title": "Grin Squint Tears",
		"library": "faregular",
		"prefix": "far",
		"tags": ["happy", "emoji", "grin"]
	},
	{
		"iconName": "file-audio",
		"title": "File Audio",
		"library": "faregular",
		"prefix": "far",
		"tags": ["document", "doc", "paper", "music"]
	},
	{
		"iconName": "calendar-xmark",
		"title": "Calendar Xmark",
		"library": "faregular",
		"prefix": "far",
		"tags": ["date", "schedule", "planner", "delete"]
	},
	{
		"iconName": "calendar-times",
		"title": "Calendar Times",
		"library": "faregular",
		"prefix": "far",
		"tags": ["date", "schedule", "planner", "delete"]
	},
	{
		"iconName": "circle-down",
		"title": "Circle Down",
		"library": "faregular",
		"prefix": "far",
		"tags": ["bottom", "descend", "south"]
	},
	{
		"iconName": "arrow-alt-circle-down",
		"title": "Arrow Alt Circle Down",
		"library": "faregular",
		"prefix": "far",
		"tags": ["bottom", "descend", "south"]
	},
	{
		"iconName": "file-lines",
		"title": "File Lines",
		"library": "faregular",
		"prefix": "far",
		"tags": ["document", "doc", "paper"]
	},
	{
		"iconName": "file-alt",
		"title": "File Alt",
		"library": "faregular",
		"prefix": "far",
		"tags": ["document", "doc", "paper"]
	},
	{
		"iconName": "file-text",
		"title": "File Text",
		"library": "faregular",
		"prefix": "far",
		"tags": ["document", "doc", "paper"]
	},
	{
		"iconName": "comments",
		"title": "Comments",
		"library": "faregular",
		"prefix": "far",
		"tags": ["reply", "message", "feedback"]
	},
	{
		"iconName": "circle-check",
		"title": "Circle Check",
		"library": "faregular",
		"prefix": "far",
		"tags": ["tick", "confirm", "done"]
	},
	{
		"iconName": "check-circle",
		"title": "Check Circle",
		"library": "faregular",
		"prefix": "far",
		"tags": ["tick", "confirm", "done"]
	},
	{
		"iconName": "moon",
		"title": "Moon",
		"library": "faregular",
		"prefix": "far",
		"tags": ["night", "dark", "sleep"]
	},
	{
		"iconName": "closed-captioning",
		"title": "Closed Captioning",
		"library": "faregular",
		"prefix": "far",
		"tags": []
	},
	{
		"iconName": "images",
		"title": "Images",
		"library": "faregular",
		"prefix": "far",
		"tags": ["photo", "picture", "media"]
	},
	{
		"iconName": "circle-right",
		"title": "Circle Right",
		"library": "faregular",
		"prefix": "far",
		"tags": ["next", "forward", "east"]
	},
	{
		"iconName": "arrow-alt-circle-right",
		"title": "Arrow Alt Circle Right",
		"library": "faregular",
		"prefix": "far",
		"tags": ["next", "forward", "east"]
	},
	{
		"iconName": "id-card",
		"title": "Id Card",
		"library": "faregular",
		"prefix": "far",
		"tags": ["id", "card", "badge"]
	},
	{
		"iconName": "drivers-license",
		"title": "Drivers License",
		"library": "faregular",
		"prefix": "far",
		"tags": ["license", "card", "badge", "car"]
	},
	{
		"iconName": "circle-play",
		"title": "Circle Play",
		"library": "faregular",
		"prefix": "far",
		"tags": ["start", "triangle", "begin"]
	},
	{
		"iconName": "play-circle",
		"title": "Play Circle",
		"library": "faregular",
		"prefix": "far",
		"tags": ["start", "triangle", "begin"]
	},
	{
		"iconName": "face-laugh-beam",
		"title": "Face Laugh Beam",
		"library": "faregular",
		"prefix": "far",
		"tags": ["laugh", "smile", "happy"]
	},
	{
		"iconName": "laugh-beam",
		"title": "Laugh Beam",
		"library": "faregular",
		"prefix": "far",
		"tags": ["laugh", "smile", "happy"]
	},
	{
		"iconName": "address-book",
		"title": "Address Book",
		"library": "faregular",
		"prefix": "far",
		"tags": ["location", "place", "contact"]
	},
	{
		"iconName": "contact-book",
		"title": "Contact Book",
		"library": "faregular",
		"prefix": "far",
		"tags": ["read", "library", "manual"]
	},
	{
		"iconName": "hourglass",
		"title": "Hourglass",
		"library": "faregular",
		"prefix": "far",
		"tags": ["hourglass", "time", "timer"]
	},
	{
		"iconName": "hourglass-empty",
		"title": "Hourglass Empty",
		"library": "faregular",
		"prefix": "far",
		"tags": ["hourglass", "time", "timer"]
	},
	{
		"iconName": "headphones",
		"title": "Headphones",
		"library": "faregular",
		"prefix": "far",
		"tags": ["headset", "audio", "listen"]
	},
	{
		"iconName": "headphones-alt",
		"title": "Headphones Alt",
		"library": "faregular",
		"prefix": "far",
		"tags": ["headset", "audio", "listen"]
	},
	{
		"iconName": "headphones-simple",
		"title": "Headphones Simple",
		"library": "faregular",
		"prefix": "far",
		"tags": ["headset", "audio", "listen"]
	},
	{
		"iconName": "file-powerpoint",
		"title": "File Powerpoint",
		"library": "faregular",
		"prefix": "far",
		"tags": ["document", "doc", "paper"]
	},
	{
		"iconName": "window-maximize",
		"title": "Window Maximize",
		"library": "faregular",
		"prefix": "far",
		"tags": ["maximize", "expand", "window"]
	},
	{
		"iconName": "comment-dots",
		"title": "Comment Dots",
		"library": "faregular",
		"prefix": "far",
		"tags": ["reply", "message", "feedback"]
	},
	{
		"iconName": "commenting",
		"title": "Commenting",
		"library": "faregular",
		"prefix": "far",
		"tags": ["reply", "message", "feedback"]
	},
	{
		"iconName": "face-grin-tongue-wink",
		"title": "Face Grin Tongue Wink",
		"library": "faregular",
		"prefix": "far",
		"tags": ["tongue", "smile", "grin"]
	},
	{
		"iconName": "grin-tongue-wink",
		"title": "Grin Tongue Wink",
		"library": "faregular",
		"prefix": "far",
		"tags": ["tongue", "smile", "grin"]
	},
	{
		"iconName": "hourglass-half",
		"title": "Hourglass Half",
		"library": "faregular",
		"prefix": "far",
		"tags": ["hourglass", "time", "timer"]
	},
	{
		"iconName": "hourglass2",
		"title": "Hourglass2",
		"library": "faregular",
		"prefix": "far",
		"tags": ["hourglass", "time", "timer"]
	},
	{
		"iconName": "credit-card",
		"title": "Credit Card",
		"library": "faregular",
		"prefix": "far",
		"tags": ["payment", "debit", "checkout"]
	},
	{
		"iconName": "credit-card-alt",
		"title": "Credit Card Alt",
		"library": "faregular",
		"prefix": "far",
		"tags": ["payment", "debit", "checkout"]
	},
	{
		"iconName": "hand-spock",
		"title": "Hand Spock",
		"library": "faregular",
		"prefix": "far",
		"tags": ["hand", "finger", "gesture"]
	},
	{
		"iconName": "bell-slash",
		"title": "Bell Slash",
		"library": "faregular",
		"prefix": "far",
		"tags": ["notification", "alert", "reminder"]
	},
	{
		"iconName": "star",
		"title": "Star",
		"library": "faregular",
		"prefix": "far",
		"tags": ["favorite", "rating", "bookmark"]
	},
	{
		"iconName": "flag",
		"title": "Flag",
		"library": "faregular",
		"prefix": "far",
		"tags": ["report", "marker", "pin"]
	},
	{
		"iconName": "lemon",
		"title": "Lemon",
		"library": "faregular",
		"prefix": "far",
		"tags": ["fruit", "food", "juicy"]
	},
	{
		"iconName": "window-restore",
		"title": "Window Restore",
		"library": "faregular",
		"prefix": "far",
		"tags": ["restore", "restore", "window"]
	},
	{
		"iconName": "face-grin-hearts",
		"title": "Face Grin Hearts",
		"library": "faregular",
		"prefix": "far",
		"tags": ["like", "love", "favorite"]
	},
	{
		"iconName": "grin-hearts",
		"title": "Grin Hearts",
		"library": "faregular",
		"prefix": "far",
		"tags": ["like", "love", "favorite"]
	},
	{
		"iconName": "face-kiss-beam",
		"title": "Face Kiss Beam",
		"library": "faregular",
		"prefix": "far",
		"tags": ["kiss", "love", "favorite"]
	},
	{
		"iconName": "kiss-beam",
		"title": "Kiss Beam",
		"library": "faregular",
		"prefix": "far",
		"tags": ["kiss", "love", "favorite"]
	},
	{
		"iconName": "file-pdf",
		"title": "File Pdf",
		"library": "faregular",
		"prefix": "far",
		"tags": ["document", "doc", "paper"]
	},
	{
		"iconName": "face-grin-wide",
		"title": "Face Grin Wide",
		"library": "faregular",
		"prefix": "far",
		"tags": ["grin", "smile", "happy"]
	},
	{
		"iconName": "grin-alt",
		"title": "Grin Alt",
		"library": "faregular",
		"prefix": "far",
		"tags": ["grin", "smile", "happy"]
	},
	{
		"iconName": "face-laugh-squint",
		"title": "Face Laugh Squint",
		"library": "faregular",
		"prefix": "far",
		"tags": ["kiss", "love", "favorite"]
	},
	{
		"iconName": "laugh-squint",
		"title": "Laugh Squint",
		"library": "faregular",
		"prefix": "far",
		"tags": ["kiss", "love", "favorite"]
	},
	{
		"iconName": "face-kiss-wink-heart",
		"title": "Face Kiss Wink Heart",
		"library": "faregular",
		"prefix": "far",
		"tags": ["like", "love", "favorite"]
	},
	{
		"iconName": "kiss-wink-heart",
		"title": "Kiss Wink Heart",
		"library": "faregular",
		"prefix": "far",
		"tags": ["like", "love", "favorite"]
	},
	{
		"iconName": "copy",
		"title": "Copy",
		"library": "faregular",
		"prefix": "far",
		"tags": ["duplicate", "clone", "replicate"]
	},
	{
		"iconName": "chess-king",
		"title": "Chess King",
		"library": "faregular",
		"prefix": "far",
		"tags": ["king", "chess", "game"]
	},
	{
		"iconName": "square-plus",
		"title": "Square Plus",
		"library": "faregular",
		"prefix": "far",
		"tags": ["add", "new", "create"]
	},
	{
		"iconName": "plus-square",
		"title": "Plus Square",
		"library": "faregular",
		"prefix": "far",
		"tags": ["add", "new", "create"]
	},
	{
		"iconName": "file-code",
		"title": "File Code",
		"library": "faregular",
		"prefix": "far",
		"tags": ["document", "doc", "paper"]
	},
	{
		"iconName": "face-grin-wink",
		"title": "Face Grin Wink",
		"library": "faregular",
		"prefix": "far",
		"tags": ["grin", "smile", "happy"]
	},
	{
		"iconName": "grin-wink",
		"title": "Grin Wink",
		"library": "faregular",
		"prefix": "far",
		"tags": ["grin", "smile", "happy"]
	},
	{
		"iconName": "money-bill1",
		"title": "Money Bill1",
		"library": "faregular",
		"prefix": "far",
		"tags": ["cash", "currency", "payment"]
	},
	{
		"iconName": "money-bill-alt",
		"title": "Money Bill Alt",
		"library": "faregular",
		"prefix": "far",
		"tags": ["cash", "currency", "payment"]
	},
	{
		"iconName": "eye-slash",
		"title": "Eye Slash",
		"library": "faregular",
		"prefix": "far",
		"tags": ["view", "see", "preview"]
	},
	{
		"iconName": "file-word",
		"title": "File Word",
		"library": "faregular",
		"prefix": "far",
		"tags": ["document", "doc", "paper"]
	},
	{
		"iconName": "face-angry",
		"title": "Face Angry",
		"library": "faregular",
		"prefix": "far",
		"tags": ["angry", "mad", "frustrated"]
	},
	{
		"iconName": "angry",
		"title": "Angry",
		"library": "faregular",
		"prefix": "far",
		"tags": ["angry", "mad", "frustrated"]
	},
	{
		"iconName": "chess-knight",
		"title": "Chess Knight",
		"library": "faregular",
		"prefix": "far",
		"tags": ["knight", "chess", "game"]
	},
	{
		"iconName": "face-grin-beam",
		"title": "Face Grin Beam",
		"library": "faregular",
		"prefix": "far",
		"tags": ["beam", "smile", "happy"]
	},
	{
		"iconName": "grin-beam",
		"title": "Grin Beam",
		"library": "faregular",
		"prefix": "far",
		"tags": ["beam", "smile", "happy"]
	},
	{
		"iconName": "hand-peace",
		"title": "Hand Peace",
		"library": "faregular",
		"prefix": "far",
		"tags": ["peace", "harmony", "balance"]
	},
	{
		"iconName": "compass",
		"title": "Compass",
		"library": "faregular",
		"prefix": "far",
		"tags": ["navigate", "direction", "bearing"]
	},
	{
		"iconName": "square",
		"title": "Square",
		"library": "faregular",
		"prefix": "far",
		"tags": ["square", "shape", "rectangle"]
	},
	{
		"iconName": "face-grin",
		"title": "Face Grin",
		"library": "faregular",
		"prefix": "far",
		"tags": ["grin", "smile", "happy"]
	},
	{
		"iconName": "grin",
		"title": "Grin",
		"library": "faregular",
		"prefix": "far",
		"tags": ["grin", "smile", "happy"]
	},
	{
		"iconName": "face-smile",
		"title": "Face Smile",
		"library": "faregular",
		"prefix": "far",
		"tags": ["smile", "happy", "joy"]
	},
	{
		"iconName": "smile",
		"title": "Smile",
		"library": "faregular",
		"prefix": "far",
		"tags": ["smile", "happy", "joy"]
	},
	{
		"iconName": "face-smile-beam",
		"title": "Face Smile Beam",
		"library": "faregular",
		"prefix": "far",
		"tags": ["smile", "happy", "joy"]
	},
	{
		"iconName": "smile-beam",
		"title": "Smile Beam",
		"library": "faregular",
		"prefix": "far",
		"tags": ["smile", "happy", "joy"]
	},
	{
		"iconName": "folder-closed",
		"title": "Folder Closed",
		"library": "faregular",
		"prefix": "far",
		"tags": ["directory", "catalog", "container"]
	},
	{
		"iconName": "keyboard",
		"title": "Keyboard",
		"library": "faregular",
		"prefix": "far",
		"tags": ["type", "input", "keys"]
	},
	{
		"iconName": "face-rolling-eyes",
		"title": "Face Rolling Eyes",
		"library": "faregular",
		"prefix": "far",
		"tags": ["view", "see", "preview"]
	},
	{
		"iconName": "meh-rolling-eyes",
		"title": "Meh Rolling Eyes",
		"library": "faregular",
		"prefix": "far",
		"tags": ["view", "see", "preview"]
	},
	{
		"iconName": "face-grimace",
		"title": "Face Grimace",
		"library": "faregular",
		"prefix": "far",
		"tags": ["grimace", "face", "expression"]
	},
	{
		"iconName": "grimace",
		"title": "Grimace",
		"library": "faregular",
		"prefix": "far",
		"tags": ["grimace", "face", "expression"]
	},
	{
		"iconName": "circle-dot",
		"title": "Circle Dot",
		"library": "faregular",
		"prefix": "far",
		"tags": ["circle", "shape", "round"]
	},
	{
		"iconName": "dot-circle",
		"title": "Dot Circle",
		"library": "faregular",
		"prefix": "far",
		"tags": ["circle", "shape", "round"]
	},
	{
		"iconName": "object-group",
		"title": "Object Group",
		"library": "faregular",
		"prefix": "far",
		"tags": ["group", "collection", "objects"]
	},
	{
		"iconName": "face-flushed",
		"title": "Face Flushed",
		"library": "faregular",
		"prefix": "far",
		"tags": ["face", "expression", "embarrassed"]
	},
	{
		"iconName": "flushed",
		"title": "Flushed",
		"library": "faregular",
		"prefix": "far",
		"tags": ["face", "expression", "embarrassed"]
	},
	{
		"iconName": "star-half-stroke",
		"title": "Star Half Stroke",
		"library": "faregular",
		"prefix": "far",
		"tags": ["favorite", "rating", "bookmark"]
	},
	{
		"iconName": "star-half-alt",
		"title": "Star Half Alt",
		"library": "faregular",
		"prefix": "far",
		"tags": ["favorite", "rating", "bookmark"]
	},
	{
		"iconName": "file-video",
		"title": "File Video",
		"library": "faregular",
		"prefix": "far",
		"tags": ["document", "doc", "paper"]
	},
	{
		"iconName": "face-laugh",
		"title": "Face Laugh",
		"library": "faregular",
		"prefix": "far",
		"tags": ["laugh", "smile", "happy"]
	},
	{
		"iconName": "laugh",
		"title": "Laugh",
		"library": "faregular",
		"prefix": "far",
		"tags": ["laugh", "smile", "happy"]
	},
	{
		"iconName": "hand-pointer",
		"title": "Hand Pointer",
		"library": "faregular",
		"prefix": "far",
		"tags": ["pointer", "hand", "gesture"]
	},
	{
		"iconName": "registered",
		"title": "Registered",
		"library": "faregular",
		"prefix": "far",
		"tags": ["copyright", "legal", "license"]
	}
]
